xyseg/document/div.py
xyseg/document/image.py
xyseg/document/pdf.py
xyseg/document/segment.py
xyseg-0.0.2.dist-info/METADATA
xyseg-0.0.2.dist-info/WHEEL
xyseg-0.0.2.dist-info/licenses/LICENSE
xyseg-0.0.2.dist-info/RECORD
