Metadata-Version: 2.3
Name: xyseg
Version: 0.0.2
Summary: Recursive Segmentation Algorithm
Project-URL: Homepage, https://github.com/johnathanchiu/recursive-segmentation
Project-URL: Issues, https://github.com/johnathanchiu/recursive-segmentation/issues
Author-email: Johnathan Chiu <johnathanchiu1065@gmail.com>
License: Apache-2.0
License-File: LICENSE
Keywords: document,images,parser,segmentation
Requires-Python: >=3.9
Requires-Dist: numpy>=2.1.1
Requires-Dist: pdfplumber>=0.11.4
Requires-Dist: pillow>=10.4.0
